<?xml version="1.0" encoding="utf-8"?>
<ms2>
	<key id="1216172113000001" npc="민트" name="이것은 기본 대사 1" />
	<key id="1216172113000002" npc="민트" name="이것은 기본 대사 2" />
	<key id="1216172113000003" npc="민트" name="이것은 기본 대사 3" />
	<key id="1216172113000004" npc="민트" name="이것은 기본 대사 4" />
	<key id="1216172113000005" npc="민트" name="이것은 기본 대사 5" />
	<key id="1216172113000006" npc="민트" name="배고파 밥줘 1" />
	<key id="1216172113000007" npc="민트" name="배고파 밥줘 2" />
	<key id="1216172113000008" npc="민트" name="나 꺼내 놓고 뭐하니 1" />
	<key id="1216172113000009" npc="민트" name="나 꺼내 놓고 뭐하니 2" />
	<key id="1216172113000010" npc="민트" name="밥 줘서 행복해 1" />
	<key id="1216172113000011" npc="민트" name="밥 줘서 행복해 2" />
	<key id="1216172113000012" npc="민트" name="스킬 쓴다! 1" />
	<key id="1216172113000013" npc="민트" name="스킬 쓴다! 2" />
	<key id="1216172113000014" npc="민트" name="물약 설정했던거 다 썼다. 1" />
	<key id="1216172113000015" npc="민트" name="물약 설정했던거 다 썼다. 2" />
	<key id="1216172113000016" npc="민트" name="주인님은 내가 살린다. 1" />
	<key id="1216172113000017" npc="민트" name="주인님은 내가 살린다. 2" />
</ms2>